setup.py
tableX/__init__.py
tableX/table2json.py
tableX.egg-info/PKG-INFO
tableX.egg-info/SOURCES.txt
tableX.egg-info/dependency_links.txt
tableX.egg-info/requires.txt
tableX.egg-info/top_level.txt
test/test.py
test/test2.py
test/test3.py
test/test4.py
test/test5.py
test/testjjw.py
test/testth.py