Metadata-Version: 2.1
Name: tableX
Version: 0.1.0
Summary: 针对前端table 工具类
Home-page: https://www.github/buliqioqiolibusdo/tablex
Author: xcc
Author-email: xinchacha@xcc.com
License: UNKNOWN
Platform: UNKNOWN
